LICENSE
MANIFEST.in
README.md
setup.cfg
setup.py
django_showurls/__init__.py
django_showurls/apps.py
django_showurls/tests.py
django_showurls.egg-info/PKG-INFO
django_showurls.egg-info/SOURCES.txt
django_showurls.egg-info/dependency_links.txt
django_showurls.egg-info/not-zip-safe
django_showurls.egg-info/requires.txt
django_showurls.egg-info/top_level.txt
django_showurls/management/__init__.py
django_showurls/management/commands/__init__.py
django_showurls/management/commands/showurls.py
django_showurls/migrations/__init__.py