Metadata-Version: 1.1
Name: django-showurls
Version: 1.0.1
Summary: Adds a mgmt command to print urls from your Django project
Home-page: https://github.com/Niklas9/django-showurls
Author: Niklas Andersson
Author-email: nandersson900@gmail.com
License: UNKNOWN
Platform: UNKNOWN
Classifier: Framework :: Django
Classifier: Intended Audience :: Developers
Classifier: Intended Audience :: System Administrators
Classifier: Operating System :: OS Independent
Classifier: Topic :: Software Development
